audiomass/__init__.py
audiomass/__main__.py
audiomass/batch_conversion.py
audiomass/comparisions.py
audiomass/datastrings.py
audiomass/dir_conversion.py
audiomass/utils.py
audiomass-0.9.6.data/data/share/audiomass/AUTHORS
audiomass-0.9.6.data/data/share/audiomass/BUGS
audiomass-0.9.6.data/data/share/audiomass/CHANGELOG
audiomass-0.9.6.data/data/share/audiomass/COPYING
audiomass-0.9.6.data/data/share/audiomass/README.md
audiomass-0.9.6.data/data/share/audiomass/TODO
audiomass-0.9.6.data/data/share/man/man1/audiomass.1.gz
audiomass-0.9.6.dist-info/AUTHORS
audiomass-0.9.6.dist-info/COPYING
audiomass-0.9.6.dist-info/METADATA
audiomass-0.9.6.dist-info/WHEEL
audiomass-0.9.6.dist-info/entry_points.txt
audiomass-0.9.6.dist-info/top_level.txt
audiomass-0.9.6.dist-info/RECORD
