Metadata-Version: 2.1
Name: audiomass
Version: 0.9.6
Summary: Wrapper for multiple audio conversion libraries. 
Home-page: https://github.com/jeanslack/audiomass
Author: Gianluca Pernigotto
Author-email: <jeanlucperni@gmail.com>
License: 'Gnu GPL3 (Gnu Public License)
Platform: Linux
Platform: Unix
Platform: MacOS
Classifier: Development Status :: 4 - Beta
Classifier: Environment :: Console
Classifier: Intended Audience :: End Users/Desktop
Classifier: License :: OSI Approved :: GNU General Public License v3 (GPLv3)
Classifier: Natural Language :: English
Classifier: Operating System :: MacOS :: MacOS X
Classifier: Operating System :: POSIX
Classifier: Programming Language :: Python :: 3
Classifier: Programming Language :: Python :: 3.6
Classifier: Programming Language :: Python :: 3.7
Classifier: Programming Language :: Python :: 3.8
Classifier: Programming Language :: Python :: 3.9
Classifier: Topic :: Multimedia :: Sound/Audio :: Conversion
Classifier: Topic :: Utilities
Requires-Python: >=3.6
License-File: COPYING
License-File: AUTHORS
